rq_exporter/__init__.py
rq_exporter/__main__.py
rq_exporter/__version__.py
rq_exporter/collector.py
rq_exporter/config.py
rq_exporter/exporter.py
rq_exporter/utils.py
rq_exporter-3.1.0.dist-info/licenses/LICENSE
rq_exporter-3.1.0.dist-info/METADATA
rq_exporter-3.1.0.dist-info/WHEEL
rq_exporter-3.1.0.dist-info/entry_points.txt
rq_exporter-3.1.0.dist-info/top_level.txt
rq_exporter-3.1.0.dist-info/RECORD
