Metadata-Version: 2.4
Name: rq-exporter
Version: 3.1.0
Summary: Prometheus exporter for Python RQ (Redis Queue)
Home-page: https://github.com/mdawar/rq-exporter
Author: Pierre Mdawar
Author-email: pierre@mdawar.dev
License: MIT
Classifier: Programming Language :: Python :: 3
Classifier: Programming Language :: Python :: 3.8
Classifier: Programming Language :: Python :: 3.9
Classifier: Programming Language :: Python :: 3.10
Classifier: Programming Language :: Python :: 3.11
Classifier: Programming Language :: Python :: 3.12
Classifier: Programming Language :: Python :: 3.13
Classifier: License :: OSI Approved :: MIT License
Classifier: Operating System :: OS Independent
Classifier: Intended Audience :: Developers
Classifier: Intended Audience :: Information Technology
Classifier: Intended Audience :: System Administrators
Classifier: Topic :: System :: Monitoring
Requires-Python: >=3.8
License-File: LICENSE
Requires-Dist: rq<3,>=2.0.0
Requires-Dist: redis<6,>=5.2.0
Requires-Dist: prometheus_client>=0.21.0
Dynamic: author
Dynamic: author-email
Dynamic: classifier
Dynamic: description
Dynamic: description-content-type
Dynamic: home-page
Dynamic: license
Dynamic: license-file
Dynamic: requires-dist
Dynamic: requires-python
Dynamic: summary
